{"type":"FeatureCollection","features":[{"type":"Feature","properties":{"Site":"Salt Fleet Flats","Type":"Restored","Image":"https://raw.githubusercontent.com/wandabodnar/phd/refs/heads/main/Sites/Salt2.jpg"},"geometry":{"coordinates":[0.5493726216590176,51.485636208833654],"type":"Point"},"id":0},{"type":"Feature","properties":{"Site":"Egypt Bay","Type":"Restored","Image":"https://raw.githubusercontent.com/wandabodnar/phd/refs/heads/main/Sites/Egypt2.jpg"},"geometry":{"coordinates":[0.5581915602622303,51.48276138843258],"type":"Point"}},{"type":"Feature","properties":{"Site":"Richmond","Type":"Degraded"},"geometry":{"coordinates":[-0.3079026469039263,51.458640972230796],"type":"Point"}}]}